sparse3d/__init__.py
sparse3d/mixins.py
sparse3d/sparse3d.py
sparse3d-1.2.11.dist-info/METADATA
sparse3d-1.2.11.dist-info/WHEEL
sparse3d-1.2.11.dist-info/licenses/LICENSE
sparse3d-1.2.11.dist-info/RECORD
